CHANGES.txt
README.txt
buildout.cfg
setup.py
bootstrap/bootstrap.py
src/megrok/__init__.py
src/megrok.genshi.egg-info/PKG-INFO
src/megrok.genshi.egg-info/SOURCES.txt
src/megrok.genshi.egg-info/dependency_links.txt
src/megrok.genshi.egg-info/entry_points.txt
src/megrok.genshi.egg-info/not-zip-safe
src/megrok.genshi.egg-info/requires.txt
src/megrok.genshi.egg-info/top_level.txt
src/megrok/genshi/__init__.py
src/megrok/genshi/components.py
src/megrok/genshi/configure.zcml
src/megrok/genshi/ftesting.zcml
src/megrok/genshi/tests/__init__.py
src/megrok/genshi/tests/test_genshitemplate.py
src/megrok/genshi/tests/static/test.css
src/megrok/genshi/tests/test_genshitemplate_templates/berries.gi
src/megrok/genshi/tests/test_genshitemplate_templates/cavepainting.g
src/megrok/genshi/tests/test_genshitemplate_templates/food.g
src/megrok/genshi/tests/test_genshitemplate_templates/gatherer.g
src/megrok/genshi/tests/test_genshitemplate_templates/hunter.gt
src/megrok/genshi/tests/test_genshitemplate_templates/static.g