Metadata-Version: 1.0
Name: megrok.genshi
Version: 1.0
Summary: Genshi integration in Grok
Home-page: http://svn.zope.org/megrok.genshi/
Author: Lennart Regebro, Guido Wesdorp
Author-email: regebro@gmail.com
License: ZPL
Keywords: grok genshi
Platform: UNKNOWN
Classifier: Development Status :: 3 - Alpha
Classifier: Environment :: Web Environment
Classifier: Intended Audience :: Developers
Classifier: License :: OSI Approved :: Zope Public License
Classifier: Programming Language :: Python
Classifier: Operating System :: OS Independent
Classifier: Topic :: Internet :: WWW/HTTP
